super_pocket/__init__.py
super_pocket/cli.py
super_pocket/interactive.py
super_pocket/settings.py
super_pocket/utils.py
super_pocket/documents/__init__.py
super_pocket/documents/cli.py
super_pocket/documents/validator.py
super_pocket/documents/cheatsheets/__init__.py
super_pocket/documents/templates/__init__.py
super_pocket/markdown/__init__.py
super_pocket/markdown/renderer.py
super_pocket/pdf/__init__.py
super_pocket/pdf/converter.py
super_pocket/project/__init__.py
super_pocket/project/req_to_date.py
super_pocket/project/to_file.py
super_pocket/project/init/__init__.py
super_pocket/project/init/actions.py
super_pocket/project/init/cli.py
super_pocket/project/init/engine.py
super_pocket/project/init/interactive.py
super_pocket/project/init/manifest.py
super_pocket/project/init/renderers.py
super_pocket/project/init/validation.py
super_pocket/project/templates/python-cli/__init__.py
super_pocket/readme/__init__.py
super_pocket/readme/badges.py
super_pocket/readme/cli.py
super_pocket/readme/detector.py
super_pocket/readme/generator.py
super_pocket/readme/models.py
super_pocket/readme/analyzers/__init__.py
super_pocket/readme/analyzers/python.py
super_pocket/readme/templates/__init__.py
super_pocket/readme/templates/base.py
super_pocket/video/cli.py
super_pocket/video/helper.py
super_pocket/video/video.py
super_pocket/web/__init__.py
super_pocket/web/favicon.py
super_pocket/web/job_search.py
super_pocket/xml/cli.py
super_pocket/xml/xml.py
super_pocket-1.1.dist-info/licenses/LICENSE
tests/__init__.py
tests/conftest.py
tests/unit_tests/__init__.py
tests/unit_tests/test_cli.py
tests/unit_tests/test_interactive_mode.py
tests/unit_tests/test_init/__init__.py
tests/unit_tests/test_init/test_actions.py
tests/unit_tests/test_init/test_engine.py
tests/unit_tests/test_init/test_interactive.py
tests/unit_tests/test_init/test_manifest.py
tests/unit_tests/test_init/test_renderers.py
tests/unit_tests/test_markdown/__init__.py
tests/unit_tests/test_markdown/test_renderer.py
tests/unit_tests/test_pdf/__init__.py
super_pocket-1.1.dist-info/METADATA
super_pocket-1.1.dist-info/WHEEL
super_pocket-1.1.dist-info/entry_points.txt
super_pocket-1.1.dist-info/top_level.txt
super_pocket-1.1.dist-info/RECORD
