Metadata-Version: 2.4
Name: super-pocket
Version: 1.1
Summary: A collection of developer tools including markdown rendering, project exporters, agent templates, and cheatsheets management.
Author-email: Dimitri Gaggioli <dimitri.gaggioli@gmail.com>
Keywords: dev-tools,cli,markdown,productivity,agents,templates,job,assistant,xml,llm
Classifier: Programming Language :: Python :: 3
Classifier: Programming Language :: Python :: 3.11
Classifier: Programming Language :: Python :: 3.12
Classifier: Programming Language :: Python :: 3.13
Classifier: Programming Language :: Python :: 3.14
Classifier: License :: OSI Approved :: MIT License
Classifier: Operating System :: OS Independent
Requires-Python: >=3.11
License-File: LICENSE
Requires-Dist: click>=8.3.1
Requires-Dist: rich-click>=1.9.4
Requires-Dist: python-dotenv>=1.2.1
Requires-Dist: requests>=2.32.5
Requires-Dist: rich>=14.2.0
Requires-Dist: httpx>=0.28.1
Requires-Dist: uvicorn>=0.38.0
Requires-Dist: fastapi>=0.121.3
Requires-Dist: jinja2>=3.1.6
Requires-Dist: pyyaml>=6.0.3
Requires-Dist: pillow>=12.0.0
Dynamic: license-file
